Metadata-Version: 2.1
Name: odoo-addon-stock_pull_list
Version: 16.0.1.0.0.5
Summary: The pull list checks the stock situation and calculates needed quantities.
Home-page: https://github.com/OCA/stock-logistics-warehouse
Author: ForgeFlow, Odoo Community Association (OCA)
Author-email: support@odoo-community.org
License: AGPL-3
Classifier: Programming Language :: Python
Classifier: Framework :: Odoo
Classifier: Framework :: Odoo :: 16.0
Classifier: License :: OSI Approved :: GNU Affero General Public License v3
Classifier: Development Status :: 4 - Beta
Requires-Python: >=3.10
Requires-Dist: odoo-addon-stock-free-quantity <16.1dev,>=16.0dev
Requires-Dist: odoo <16.1dev,>=16.0a
